capapi
