Metadata-Version: 2.1
Name: capapi
Version: 0.0.6
Summary: Capitalism API wrapper in Python
Home-page: https://github.com/drapespy/CapAPI
Author: drapes
Author-email: lildrapesbusiness@gmail.com
License: MIT
Keywords: python,capitalism,api wrapper,api,wrapper,capi,capi.py
Platform: UNKNOWN
Classifier: Development Status :: 1 - Planning
Classifier: Intended Audience :: Developers
Classifier: Programming Language :: Python :: 3
Classifier: Operating System :: Unix
Classifier: Operating System :: MacOS :: MacOS X
Classifier: Operating System :: Microsoft :: Windows
Requires-Python: >=3.5.3
License-File: LICENSE
